{
  "users": [
    {
      "id": "user1",
      "username": "test1",
      "password": "1234",
      "name": "철수",
      "balance": 1000000,
      "layoutId": 1
    },
    {
      "id": "user2",
      "username": "test2",
      "password": "1234",
      "name": "영희",
      "balance": 500000,
      "layoutId": 2
    },
    {
      "username": "test",
      "name": "정준",
      "password": "1234",
      "balance": 0,
      "layoutId": 1,
      "id": "n6K3AIp"
    },
    {
      "username": "jjeong2",
      "name": "준",
      "password": "1234",
      "balance": 0,
      "layoutId": 1,
      "id": "-yx5KNy"
    }
  ],
  "transactions": [
    {
      "id": 1,
      "userId": "user1",
      "type": "income",
      "amount": 50000,
      "date": "2026-04-01",
      "title": "용돈",
      "categoryId": 3,
      "paymentMethod": "현금",
      "memo": "주간 용돈"
    },
    {
      "id": 2,
      "userId": "user1",
      "type": "expense",
      "amount": 10000,
      "date": "2026-04-02",
      "title": "커피",
      "categoryId": 2,
      "paymentMethod": "신용카드",
      "memo": "",
      "isFixed": false
    },
    {
      "id": 3,
      "userId": "user2",
      "type": "income",
      "amount": 200000,
      "date": "2026-04-01",
      "title": "월급"
    },
    {
      "id": 4,
      "userId": "user1",
      "type": "expense",
      "amount": 1250,
      "date": "2026-04-03",
      "title": "지하철 요금",
      "categoryId": 5,
      "paymentMethod": "교통카드",
      "memo": "학원 등교",
      "isFixed": true
    },
    {
      "id": 5,
      "userId": "user1",
      "type": "income",
      "amount": 12000,
      "date": "2026-04-05",
      "title": "교보문고",
      "categoryId": 3,
      "paymentMethod": null,
      "memo": "",
      "isFixed": false
    },
    {
      "id": 6,
      "userId": "user1",
      "type": "expense",
      "amount": 4900,
      "date": "2026-04-06",
      "title": "편의점 간식",
      "categoryId": 1,
      "paymentMethod": "현금",
      "memo": "초콜릿",
      "isFixed": false
    },
    {
      "userId": "user1",
      "type": "income",
      "amount": 234,
      "categoryId": 3,
      "paymentMethod": "현금",
      "date": "2026-04-08",
      "memo": "234",
      "isFixed": false,
      "id": 7
    },
    {
      "userId": "user1",
      "type": "income",
      "amount": 43234,
      "categoryId": 3,
      "paymentMethod": "현금",
      "date": "2026-04-16",
      "memo": "432234",
      "isFixed": false,
      "id": 8
    }
  ],
  "catgories": [
    {
      "id": 1,
      "name": "급여"
    },
    {
      "id": 2,
      "name": "상여"
    },
    {
      "id": 3,
      "name": "용돈"
    },
    {
      "id": 4,
      "name": "부동산"
    },
    {
      "id": 5,
      "name": "금융"
    },
    {
      "id": 6,
      "name": "기타"
    },
    {
      "id": 7,
      "name": "식비"
    },
    {
      "id": 8,
      "name": "패션/쇼핑"
    },
    {
      "id": 9,
      "name": "뷰티/미용"
    },
    {
      "id": 10,
      "name": "교통"
    },
    {
      "id": 11,
      "name": "주거/통신"
    },
    {
      "id": 12,
      "name": "의료/건강"
    },
    {
      "id": 13,
      "name": "문화/여행"
    },
    {
      "id": 14,
      "name": "경조/선물"
    },
    {
      "id": 15,
      "name": "반려동물"
    },
    {
      "id": 16,
      "name": "기타"
    }
  ],
  "budgets": [
    {
      "id": 1,
      "userId": "user1",
      "amount": 2000000,
      "month": "2026-04"
    }
  ],
  "paymentMethods": [],
  "layout": [
    {
      "id": 1,
      "shape": "normal"
    },
    {
      "id": 2,
      "shape": "minimal"
    },
    {
      "id": 3,
      "shape": "goal"
    },
    {
      "id": 4,
      "shape": "analysis"
    }
  ]
}
